ai_image/__init__.py
ai_images-0.1.1.dist-info/METADATA
ai_images-0.1.1.dist-info/WHEEL
ai_images-0.1.1.dist-info/top_level.txt
ai_images-0.1.1.dist-info/RECORD
