Metadata-Version: 2.1
Name: ai-images
Version: 0.1.1
Summary: UNKNOWN
Home-page: https://github.com/keithhb33/AI-Image-Bot/
Author: Keith Burroughs
Author-email: keithburroughs33@gmail.com
License: UNKNOWN
Keywords: python,images,ai,ai generated,movies,photography,modules
Platform: UNKNOWN
Requires-Dist: requests
